Workbook
Name Beneficio_Neto: #REF!
Name Costo_Pct: #REF!
Name Gastos_Fijos: #REF!
Name Margen_Bruto: #REF!
Name SegmentaciónDeDatos_Ciudad: #N/A
Name SegmentaciónDeDatos_Familia: #N/A
Name SegmentaciónDeDatos_Nro_Mes: #N/A
Name Var_Demanda: #REF!
Name Var_Precio: #REF!
Name Venta_2027: #REF!
Name Venta_base: #REF!

Sheet Dashboard Final
B1: Performance Comercial Vs Metas 2026
B3: =Soporte_Dashboard!Q14&" 2026 · Venta neta $ "&TEXT(Soporte_Dashboard!N3/1000000,"0,0")&" M · "&TEXT(Soporte_Dashboard!N5,"0%")&" de la meta" -> Enero–Julio (7 meses) 2026 · Venta neta $ 218,2 M · 87% de la meta
B5: Venta Neta | F5: Cumplimiento vs meta | J5: Precio Promedio x Kilo | N5: NC %
B6: =Soporte_Dashboard!$N$3 -> 2.1820811e+08 | F6: =Soporte_Dashboard!$N$5 -> 0.87283242 | J6: =Soporte_Dashboard!$N$6 -> 8889.6899 | N6: =Soporte_Dashboard!N7 -> 0.030944375
B7: La venta total menos las NC | F7: ="Meta: $ "&TEXT(Soporte_Dashboard!$N$4/1000000,"0,0")&" M" -> Meta: $ 250,0 M | J7: Fact $ sobre la cantidad Kilos del producto | N7: Porcentaje de devoluciones en $
L21: Lectura:
L23: =Soporte_Dashboard!Q10 -> 2 de 7 meses superan la meta, con pico en Marzo
L25: =Soporte_Dashboard!Q11 -> Comodoro Rivadavia concentra el 37% de la venta
L27: =Soporte_Dashboard!Q12 -> De cada $100 vendidos, quedan $34 de margen bruto

Sheet Soporte_Dashboard
B2: Meses | C2: Total Ventas | D2: Meta Ventas | E2: Cumplimiento % | G2: Ciudad | H2: Total Ventas | J2: Para Cascada | M2: Para Kpis: | P2: Para el texto:
B3: Enero | C3: 21780524 | D3: 35714286 | E3: 0.60985468 | G3: Cañadon Seco | H3: 60415.32 | J3: Venta bruta | K3: =CUBEVALUE("ThisWorkbookDataModel","[Measures].[Ventas Brutas]",SegmentaciónDeDatos_Familia,SegmentaciónDeDatos_Ciudad,SegmentaciónDeDatos_Nro_Mes) -> 2.2517604e+08 | M3: Venta Neta | N3: =CUBEVALUE("ThisWorkbookDataModel","[Measures].[Total Ventas]",SegmentaciónDeDatos_Familia,SegmentaciónDeDatos_Ciudad,SegmentaciónDeDatos_Nro_Mes) -> 2.1820811e+08 | P3: Meses con Venta | Q3: =COUNTIFS(E:E,">0",B:B,"<>Total general") -> 7
B4: Febrero | C4: 39902338 | D4: 35714286 | E4: 1.1172655 | G4: Las Heras | H4: 162994.35 | J4: Notas de credito | K4: =CUBEVALUE("ThisWorkbookDataModel","[Measures].[Notas de Credito]",SegmentaciónDeDatos_Familia,SegmentaciónDeDatos_Ciudad,SegmentaciónDeDatos_Nro_Mes) -> -6967931.8 | M4: Meta | N4: =CUBEVALUE("ThisWorkbookDataModel","[Measures].[Meta Ventas]",SegmentaciónDeDatos_Familia,SegmentaciónDeDatos_Ciudad,SegmentaciónDeDatos_Nro_Mes) -> 2.5e+08 | P4: Meses con Sobre Venta | Q4: =COUNTIFS(E:E,">=1",B:B,"<>Total general") -> 2
B5: Marzo | C5: 47783921 | D5: 35714286 | E5: 1.3379498 | G5: Puerto San Julian | H5: 256014.96 | J5: Venta Neta | K5: =+K4+K3 -> 2.1820811e+08 | M5: Cumplimiento | N5: =+N3/N4 -> 0.87283242 | P5: Venta Mejor Mes | Q5: =_xlfn.MAXIFS(C:C,B:B,"<>Total general") -> 47783921
B6: Abril | C6: 21130082 | D6: 35714286 | E6: 0.59164231 | G6: Los Antiguos | H6: 443991.35 | J6: Costo (65%) | K6: =-K5*0.65 -> -1.4183527e+08 | M6: Precio x kg | N6: =CUBEVALUE("ThisWorkbookDataModel","[Measures].[Precio Prom x Kg]",SegmentaciónDeDatos_Familia,SegmentaciónDeDatos_Ciudad,SegmentaciónDeDatos_Nro_Mes) -> 8889.6899 | P6: Mejor Mes | Q6: =INDEX(B:B,MATCH(Q5,C:C,0)) -> Marzo
B7: Mayo | C7: 29420374 | D7: 35714286 | E7: 0.82377048 | G7: Rada Tilly | H7: 11857140 | J7: Margen bruto | K7: =+K5+K6 -> 76372837 | M7: NC % venta bruta | N7: =IFERROR(-K4/K3,"Sin NC") -> 0.030944375 | P7: Venta Top Ciudad | Q7: =_xlfn.MAXIFS(H:H,G:G,"<>Total general") -> 80757229
B8: Junio | C8: 29407933 | D8: 35714286 | E8: 0.82342212 | G8: Sarmiento | H8: 19207347 | P8: Top Ciudad | Q8: =INDEX(G:G,MATCH(Q7,H:H,0)) -> Comodoro Rivadavia
B9: Julio | C9: 28782932 | D9: 35714286 | E9: 0.80592211 | G9: Pico Truncado | H9: 26530901
B10: Total general | C10: 2.1820811e+08 | D10: 2.5e+08 | E10: 0.87283242 | G10: Puerto Deseado | H10: 35479799 | P10: Link 1 | Q10: =IF(Q4=0,"Ningún mes alcanza la meta en la selección",Q4&" de "&Q3&" meses superan la meta, con pico en "&Q6) -> 2 de 7 meses superan la meta, con pico en Marzo
G11: Caleta Olivia | H11: 43452273 | P11: Link 2 | Q11: =Q8&" concentra el "&TEXT(Q7/VLOOKUP("Total general",G:H,2,0),"0%")&" de la venta" -> Comodoro Rivadavia concentra el 37% de la venta
G12: Comodoro Rivadavia | H12: 80757229 | P12: Link 3 | Q12: ="De cada $100 vendidos, quedan $"&TEXT(K7/K3*100,"0")&" de margen bruto" -> De cada $100 vendidos, quedan $34 de margen bruto
G13: Total general | H13: 2.1820811e+08
Q14: {=IF(Q3=1,B3,B3&"–"&INDEX(B:B,2+Q3)&" ("&Q3&" meses)")} -> Enero–Julio (7 meses)

Sheet Config
A1: Ruta
A2: {=LEFT(CELL("nombrearchivo",A1),SEARCH("[",CELL("nombrearchivo",A1))-1)} -> C:\Users\z\Desktop\Curso\1 Excel\9. Modulo 9\
